stratetrees/__init__.py
stratetrees/loaders.py
stratetrees/models.py
stratetrees/nodes.py
stratetrees-0.0.1.dist-info/METADATA
stratetrees-0.0.1.dist-info/WHEEL
stratetrees-0.0.1.dist-info/licenses/LICENSE
stratetrees-0.0.1.dist-info/RECORD
