Metadata-Version: 2.1
Name: stratetrees
Version: 0.0.1
Summary: A package for importing UPPAAL Stratego strategies as Python objects
Project-URL: Homepage, https://github.com/andreashhpetersen/stratetrees
Project-URL: Bug Tracker, https://github.com/andreashhpetersen/stratetrees/issues
Author-email: Andreas Holck Høeg-Petersen <ahhp@cs.aau.dk>
License-File: LICENSE
Classifier: License :: OSI Approved :: MIT License
Classifier: Operating System :: OS Independent
Classifier: Programming Language :: Python :: 3
Requires-Python: >=3.7
Requires-Dist: numpy
Requires-Dist: pydot
